{
    "currentPage": 1,
    "data": [{
        "id": 31,
        "logo": "/images/temp/ad1.jpg",
        "name": "摩羯座001",
        "templateDtl": [{
            "unit": "分钟",
            "title": "身体放松坐",
            "amounts": 6,
            "describe": "身体放松坐",
            "money": "5"
        }, {
            "unit": "分钟",
            "title": "身体恢复坐",
            "amounts": 10,
            "describe": "身体恢复坐",
            "money": "8"
        }, {
            "unit": "分钟",
            "title": "身体缓解坐",
            "amounts": 15,
            "describe": "身体缓解坐",
            "money": "10"
        }]
    },{
        "id": 32,
        "logo": "/images/temp/ad1.jpg",
        "name": "摩羯座002",
        "templateDtl": [{
            "unit": "分钟",
            "title": "身体放松坐",
            "amounts": 6,
            "describe": "身体放松坐",
            "money": "5"
        }, {
            "unit": "分钟",
            "title": "身体恢复坐",
            "amounts": 10,
            "describe": "身体恢复坐",
            "money": "8"
        }, {
            "unit": "分钟",
            "title": "身体缓解坐",
            "amounts": 15,
            "describe": "身体缓解坐",
            "money": "10"
        }]
    }],
    "exception": "",
    "funcId": "MXZ030005",
    "homedir": "",
    "pageSize": 10,
    "resultCode": "0000",
    "resultMsg": "操作成功",
    "totalCount": 0,
    "totalPage": 1
}
